README.txt
setup.py
Products/__init__.py
Products.ImageCaptionValidator.egg-info/PKG-INFO
Products.ImageCaptionValidator.egg-info/SOURCES.txt
Products.ImageCaptionValidator.egg-info/dependency_links.txt
Products.ImageCaptionValidator.egg-info/entry_points.txt
Products.ImageCaptionValidator.egg-info/namespace_packages.txt
Products.ImageCaptionValidator.egg-info/not-zip-safe
Products.ImageCaptionValidator.egg-info/requires.txt
Products.ImageCaptionValidator.egg-info/top_level.txt
Products/ImageCaptionValidator/__init__.py
Products/ImageCaptionValidator/changes.txt
Products/ImageCaptionValidator/readme.txt
Products/ImageCaptionValidator/validator.py
Products/ImageCaptionValidator/_darcs/format
Products/ImageCaptionValidator/_darcs/hashed_inventory
Products/ImageCaptionValidator/_darcs/index_invalid
Products/ImageCaptionValidator/_darcs/tentative_pristine
Products/ImageCaptionValidator/_darcs/inventories/0000000186-22a7f780f39704024d564d5a663386192cfd7834fd55a52ae560a0153eb20a52
Products/ImageCaptionValidator/_darcs/inventories/0000000440-32afa0ab8aae1ef03e244e852bbe6d51e178790f33dae9ed6d383f5119714b33
Products/ImageCaptionValidator/_darcs/patches/0000001338-5a68c39b30b801f9183edea38e21311e6b6c985c6bac0ea85d8070866640030b
Products/ImageCaptionValidator/_darcs/patches/0000001829-325186a1d4d8e20cf2788918bb000c39368a699b5ee41059e2eef8b6c6de61e2
Products/ImageCaptionValidator/_darcs/patches/pending
Products/ImageCaptionValidator/_darcs/patches/pending.tentative
Products/ImageCaptionValidator/_darcs/prefs/author
Products/ImageCaptionValidator/_darcs/prefs/binaries
Products/ImageCaptionValidator/_darcs/prefs/boring
Products/ImageCaptionValidator/_darcs/prefs/motd
Products/ImageCaptionValidator/_darcs/pristine.hashed/0000000017-37ea5591c170ae865da606d07251d3de3c8d944f78764a1cf69ef7fecfcc964a
Products/ImageCaptionValidator/_darcs/pristine.hashed/0000000189-5b539e9ef22bdc2dda0a6c4f1be65114bbe56e82648d2bd8adf77c65728f80b1
Products/ImageCaptionValidator/_darcs/pristine.hashed/0000000189-8a34ba5d66badcea2a76dc29e4bbbd7bdd74f4af119f0aff4eadfccb1df6ea4e
Products/ImageCaptionValidator/_darcs/pristine.hashed/0000001098-e34aec007f5102fc636c864cfd8243d5f4754d1ea927c8de9e9dab3cc7daf01a
Products/ImageCaptionValidator/_darcs/pristine.hashed/0000001448-7cd08c80f3636b24e48176ac99bfedc077fcc3e5a91733a987b72fd126eda704
Products/ImageCaptionValidator/_darcs/pristine.hashed/da39a3ee5e6b4b0d3255bfef95601890afd80709
