Metadata-Version: 1.0
Name: Products.ImageCaptionValidator
Version: 1.0b2
Summary: Validator that checks imageCaption is set, if an image has been added either directly or via a reference
Home-page: http://www.nidelven-it.no/d
Author: Nidelven IT
Author-email: info@nidelven-it.no
License: GPL
Keywords: python plone archetypes validation
Platform: UNKNOWN
Classifier: Programming Language :: Python
Classifier: Framework :: Zope2
Classifier: Framework :: Plone
